<?xml version="1.0"?>
<preset version="8"><type>image</type><comment>Creates 8-bit Jpeg file sequence numbered based on the timecode of the selected clip.</comment><video><fileType>Jpeg</fileType><codec>923688</codec><codecProfile></codecProfile><namePattern>&lt;name&gt;/&lt;name&gt;.</namePattern><compressionQuality>100</compressionQuality><includeAlpha>False</includeAlpha><overwriteWithVersions>False</overwriteWithVersions><posterFrame>False</posterFrame><useFrameAsPoster>1</useFrameAsPoster><resize><resizeType>fit</resizeType><resizeFilter>lanczos</resizeFilter><width>0</width><height>0</height><bitsPerChannel>8</bitsPerChannel><numChannels>3</numChannels><floatingPoint>False</floatingPoint><bigEndian>True</bigEndian><pixelRatio>1</pixelRatio><scanFormat>P</scanFormat></resize></video><name><framePadding>4</framePadding><startFrame>1</startFrame><frameIndex>0</frameIndex></name></preset>